dong_screen_orc2txt/__init__.py
dong_screen_orc2txt/recognizer.py
dong_screen_orc2txt-0.0.5.dist-info/METADATA
dong_screen_orc2txt-0.0.5.dist-info/WHEEL
dong_screen_orc2txt-0.0.5.dist-info/top_level.txt
dong_screen_orc2txt-0.0.5.dist-info/RECORD
